fourier_dhx/__init__.py
fourier_dhx/sdk/DexHand.py
fourier_dhx/sdk/Hand.py
fourier_dhx/sdk/InspireHand.py
fourier_dhx/sdk/__init__.py
fourier_dhx-0.0.2.dist-info/LICENSE.txt
fourier_dhx-0.0.2.dist-info/METADATA
fourier_dhx-0.0.2.dist-info/WHEEL
fourier_dhx-0.0.2.dist-info/top_level.txt
fourier_dhx-0.0.2.dist-info/RECORD
