Metadata-Version: 2.1
Name: fourier-dhx
Version: 0.0.2
Summary: A smart sdk for fourier dexterous hand example package
Author: Fei liu, Jinglue Hang
Author-email: jinglue.hang@fftai.com
Classifier: Programming Language :: Python :: 3
Classifier: License :: OSI Approved :: MIT License
Classifier: Operating System :: OS Independent
Requires-Python: >=3.6
License-File: LICENSE.txt
